aiodevision/__init__.py
aiodevision/client.py
aiodevision/dataclasses.py
aiodevision-0.2.4.dist-info/LICENSE
aiodevision-0.2.4.dist-info/WHEEL
aiodevision-0.2.4.dist-info/METADATA
aiodevision-0.2.4.dist-info/RECORD
